netconf_proxy_logger/__init__.py
netconf_proxy_logger/handler.py
netconf_proxy_logger/server.py
netconf_proxy_logger-0.1.0.dist-info/LICENSE
netconf_proxy_logger-0.1.0.dist-info/METADATA
netconf_proxy_logger-0.1.0.dist-info/WHEEL
netconf_proxy_logger-0.1.0.dist-info/entry_points.txt
netconf_proxy_logger-0.1.0.dist-info/top_level.txt
netconf_proxy_logger-0.1.0.dist-info/RECORD
