Metadata-Version: 2.1
Name: netconf-proxy-logger
Version: 0.1.0
Summary: A NETCONF proxy server with comprehensive logging capabilities
Home-page: https://github.com/SATYAJIT1910/netconf-proxy-logger
Author: Satyajit Ghosh
Author-email: contact@satyajit.co.in
Keywords: netconf proxy logging network automation
Classifier: Development Status :: 3 - Alpha
Classifier: Intended Audience :: Developers
Classifier: Intended Audience :: System Administrators
Classifier: License :: OSI Approved :: MIT License
Classifier: Programming Language :: Python :: 3.11
Classifier: Topic :: System :: Networking
Requires-Python: >=3.11
License-File: LICENSE
Requires-Dist: paramiko<4.0.0,>=3.1.0
